ohoh/middleware.py
ohoh/tbutil.py
ohoh/VERSION.txt
ohoh/wsgi.py
ohoh/__init__.py
ohoh/clients/httpie.py
ohoh/clients/__init__.py
ohoh-0.1.0.dist-info/DESCRIPTION.rst
ohoh-0.1.0.dist-info/entry_points.txt
ohoh-0.1.0.dist-info/METADATA
ohoh-0.1.0.dist-info/metadata.json
ohoh-0.1.0.dist-info/RECORD
ohoh-0.1.0.dist-info/top_level.txt
ohoh-0.1.0.dist-info/WHEEL
