Metadata-Version: 2.0
Name: ohoh
Version: 0.1.0
Summary: A debug server for WSGI apps.
Home-page: https://github.com/te-je/ohoh
Author: Te-je Rodgers
Author-email: tjd.rodgers@gmail.com
License: MIT
Requires-Dist: server-reloader
Requires-Dist: tblib
Requires-Dist: pyjwt (>=1.0.1)
Requires-Dist: dill
Provides-Extra: client_tools
Requires-Dist: requests; extra == 'client_tools'
Provides-Extra: httpie_plugin
Requires-Dist: httpie; extra == 'httpie_plugin'
Requires-Dist: pygments; extra == 'httpie_plugin'
Requires-Dist: requests; extra == 'httpie_plugin'
